parzenpy/__init__.py
parzenpy/parzen_smooth.py
parzenpy-1.0.0.dist-info/LICENSE
parzenpy-1.0.0.dist-info/METADATA
parzenpy-1.0.0.dist-info/WHEEL
parzenpy-1.0.0.dist-info/top_level.txt
parzenpy-1.0.0.dist-info/RECORD
