Metadata-Version: 2.1
Name: parzenpy
Version: 1.0.0
Summary: A package for applying smoothing to frequency spectra
Home-page: https://github.com/fjornelas/parzenpy
Author: Francisco Javier Ornelas
Author-email: jornela1@g.ucla.edu
License: UNKNOWN
Project-URL: Bug Reports, https://github.com/fjornelas/parzenpy/issues
Project-URL: Source, https://github.com/fjornelas/parzenpy
Keywords: parzen spectral smoothing
Platform: UNKNOWN
Classifier: Development Status :: 5 - Production/Stable
Classifier: Intended Audience :: Developers
Classifier: Intended Audience :: Education
Classifier: Intended Audience :: Science/Research
Classifier: Topic :: Education
Classifier: Topic :: Scientific/Engineering
Classifier: Topic :: Scientific/Engineering :: Physics
Classifier: License :: OSI Approved :: GNU General Public License v3 or later (GPLv3+)
Classifier: Programming Language :: Python :: 3.6
Classifier: Programming Language :: Python :: 3.7
Classifier: Programming Language :: Python :: 3.8
Classifier: Programming Language :: Python :: 3.9
Requires-Python: >=3.8
License-File: LICENSE
Requires-Dist: numpy
